setup.py
objects/Arg.py
objects/Docstring.py
objects/Return.py
objects/Route.py
objects/Signature.py
objects/__init__.py
objects/__main__.py
objects/pygger.py
pygger.egg-info/PKG-INFO
pygger.egg-info/SOURCES.txt
pygger.egg-info/dependency_links.txt
pygger.egg-info/not-zip-safe
pygger.egg-info/top_level.txt