Metadata-Version: 1.0
Name: pygger
Version: 0.213
Summary: Swagger doc generator for python code
Home-page: https://github.com/GBernard314/pygger
Author: GBernard314
Author-email: guillaume.bernard31415@gmail.com
License: MIT
Platform: UNKNOWN
